cx_studio/__init__.py
cx_studio/py.typed
cx_studio/core/__init__.py
cx_studio/core/cx_datapackage.py
cx_studio/core/cx_filesize.py
cx_studio/core/cx_time.py
cx_studio/core/cx_timebase.py
cx_studio/core/cx_timerange.py
cx_studio/core/py.typed
cx_studio/ffmpeg/__init__.py
cx_studio/ffmpeg/cx_ff_common.py
cx_studio/ffmpeg/cx_ff_errors.py
cx_studio/ffmpeg/cx_ff_infos.py
cx_studio/ffmpeg/cx_ffmpeg.py
cx_studio/ffmpeg/cx_ffmpeg_async.py
cx_studio/locales/en_US/LC_MESSAGES/messages.po
cx_studio/path_expander/__init__.py
cx_studio/path_expander/cx_cmdfinder.py
cx_studio/path_expander/cx_emptydirvalidator.py
cx_studio/path_expander/cx_executablevalidator.py
cx_studio/path_expander/cx_pathexpander.py
cx_studio/path_expander/cx_pathvalidator.py
cx_studio/path_expander/cx_suffixvalidator.py
cx_studio/path_expander/py.typed
cx_studio/tag_replacer/__init__.py
cx_studio/tag_replacer/cx_pathinfoprovider.py
cx_studio/tag_replacer/cx_standardfolderprovider.py
cx_studio/tag_replacer/cx_tagpattern.py
cx_studio/tag_replacer/cx_tagreplacer.py
cx_studio/tag_replacer/py.typed
cx_studio/utils/__init__.py
cx_studio/utils/cx_encoding.py
cx_studio/utils/cx_functionalutils.py
cx_studio/utils/cx_numberutils.py
cx_studio/utils/cx_pathutils.py
cx_studio/utils/cx_streamutils.py
cx_studio/utils/cx_streamutils_async.py
cx_studio/utils/cx_textutils.py
cx_studio/utils/py.typed
cx_studio/utils/tools/__init__.py
cx_studio/utils/tools/async_canceller.py
cx_studio/utils/tools/double_trigger.py
cx_studio/utils/tools/job_counter.py
cx_studio-0.2.1.9.dist-info/METADATA
cx_studio-0.2.1.9.dist-info/WHEEL
cx_studio-0.2.1.9.dist-info/licenses/LICENSE
cx_studio-0.2.1.9.dist-info/RECORD
