Metadata-Version: 2.4
Name: cx-studio
Version: 0.2.1.9
Summary: A Python library for interacting with the CX Studio API
License-File: LICENSE
Requires-Python: >=3.12
Requires-Dist: chardet>=5.2.0
Requires-Dist: lazy-object-proxy>=1.10.0
Requires-Dist: pydantic>=2.11.4
Requires-Dist: pyee>=13.0.0
